search_common/__init__.py
search_common/document_set.py
search_common/hashlib.py
search_common/test_hashlib.py
search_common-0.1.3.dist-info/METADATA
search_common-0.1.3.dist-info/WHEEL
search_common-0.1.3.dist-info/top_level.txt
search_common-0.1.3.dist-info/RECORD
