Metadata-Version: 2.1
Name: search-common
Version: 0.1.3
Summary: Search common package.
Home-page: https://www.search.com
Author: Search Inc
Author-email: hi@search.com
License: Apache License, Version 2.0
Keywords: search common
Platform: UNKNOWN
Classifier: Development Status :: 3 - Alpha
Classifier: Intended Audience :: Developers
Classifier: Natural Language :: English
Classifier: Operating System :: POSIX :: Linux
Classifier: Programming Language :: Python :: 3.6
Classifier: License :: OSI Approved :: Apache Software License
